{"cameraMode":{"drawMode":0,"name":"Shaded","section":"Shading Mode"},"sceneLighting":false,"audioPlay":false,"sceneViewState":{"m_AlwaysRefresh":false,"showFog":false,"showSkybox":false,"showFlares":true,"showImageEffects":true,"showParticleSystems":true,"showVisualEffectGraphs":true,"m_FxEnabled":true},"in2DMode":false,"pivot":{"x":0.0010000000474974514,"y":-0.43799999356269839,"z":-0.4580000042915344},"rotation":{"x":-0.10609619319438935,"y":0.8380843997001648,"z":-0.1760358065366745,"w":-0.5054575204849243},"size":10.0,"orthographic":false}